Workbook

Sheet Base Case Forecast
A1: Base Case Forecast
A3: Month | B3: Revenue | C3: Cost of Services | D3: Marketing | E3: Operating Expenses | F3: Net Operating Profit | H3: Revenue Check
A4: Month 1 | B4: =Assumptions!$B$3 -> 500000 | C4: =B4*Assumptions!$B$7 -> 150000 | D4: =B4*Assumptions!$B$8 -> 50000 | E4: =Assumptions!$B$10 -> 100000 | F4: =B4-C4-D4-E4 -> 200000 | H4: Month 1 Revenue | I4: 500000
A5: Month 2 | B5: =B4*(1+Assumptions!$B$4) -> 525000 | C5: =B5*Assumptions!$B$7 -> 157500 | D5: =B5*Assumptions!$B$8 -> 52500 | E5: =Assumptions!$B$10 -> 100000 | F5: =B5-C5-D5-E5 -> 215000 | H5: Monthly Growth | I5: 0.05
A6: Month 3 | B6: =B5*(1+Assumptions!$B$4) -> 551250 | C6: =B6*Assumptions!$B$7 -> 165375 | D6: =B6*Assumptions!$B$8 -> 55125 | E6: =Assumptions!$B$10 -> 100000 | F6: =B6-C6-D6-E6 -> 230750 | H6: Month 12 Revenue | I6: =B15 -> 855169.68
A7: Month 4 | B7: =B6*(1+Assumptions!$B$4) -> 578812.5 | C7: =B7*Assumptions!$B$7 -> 173643.75 | D7: =B7*Assumptions!$B$8 -> 57881.25 | E7: =Assumptions!$B$10 -> 100000 | F7: =B7-C7-D7-E7 -> 247287.5
A8: Month 5 | B8: =B7*(1+Assumptions!$B$4) -> 607753.12 | C8: =B8*Assumptions!$B$7 -> 182325.94 | D8: =B8*Assumptions!$B$8 -> 60775.312 | E8: =Assumptions!$B$10 -> 100000 | F8: =B8-C8-D8-E8 -> 264651.88
A9: Month 6 | B9: =B8*(1+Assumptions!$B$4) -> 638140.78 | C9: =B9*Assumptions!$B$7 -> 191442.23 | D9: =B9*Assumptions!$B$8 -> 63814.078 | E9: =Assumptions!$B$10 -> 100000 | F9: =B9-C9-D9-E9 -> 282884.47 | H9: Base Case Forecast Assumptions
A10: Month 7 | B10: =B9*(1+Assumptions!$B$4) -> 670047.82 | C10: =B10*Assumptions!$B$7 -> 201014.35 | D10: =B10*Assumptions!$B$8 -> 67004.782 | E10: =Assumptions!$B$11 -> 120000 | F10: =B10-C10-D10-E10 -> 282028.69
A11: Month 8 | B11: =B10*(1+Assumptions!$B$4) -> 703550.21 | C11: =B11*Assumptions!$B$7 -> 211065.06 | D11: =B11*Assumptions!$B$8 -> 70355.021 | E11: =Assumptions!$B$11 -> 120000 | F11: =B11-C11-D11-E11 -> 302130.13 | H11: Starting Revenue (Month 1) | I11: 500000 | J11: Given
A12: Month 9 | B12: =B11*(1+Assumptions!$B$4) -> 738727.72 | C12: =B12*Assumptions!$B$7 -> 221618.32 | D12: =B12*Assumptions!$B$8 -> 73872.772 | E12: =Assumptions!$B$11 -> 120000 | F12: =B12-C12-D12-E12 -> 323236.63 | H12: Monthly Revenue Growth | I12: 0.05 | J12: Given
A13: Month 10 | B13: =B12*(1+Assumptions!$B$4) -> 775664.11 | C13: =B13*Assumptions!$B$7 -> 232699.23 | D13: =B13*Assumptions!$B$8 -> 77566.411 | E13: =Assumptions!$B$11 -> 120000 | F13: =B13-C13-D13-E13 -> 345398.46 | H13: Forecast Period (Months) | I13: 12 | J13: Given
A14: Month 11 | B14: =B13*(1+Assumptions!$B$4) -> 814447.31 | C14: =B14*Assumptions!$B$7 -> 244334.19 | D14: =B14*Assumptions!$B$8 -> 81444.731 | E14: =Assumptions!$B$11 -> 120000 | F14: =B14-C14-D14-E14 -> 368668.39 | H14: Cost of Services (% of Revenue) | J14: Not provided in the attached instructions
A15: Month 12 | B15: =B14*(1+Assumptions!$B$4) -> 855169.68 | C15: =B15*Assumptions!$B$7 -> 256550.9 | D15: =B15*Assumptions!$B$8 -> 85516.968 | E15: =Assumptions!$B$11 -> 120000 | F15: =B15-C15-D15-E15 -> 393101.81 | H15: Marketing Expense (% of Revenue) | I15: 0.3 | J15: Base-case assumption: 30% of monthly revenue
H16: Marketing Expense (Fixed Monthly Amount) | I16: 0.1 | J16: Base-case assumption: 10% of monthly revenue
H17: Operating Expenses (Months 1–6) | J17: Not used because marketing is modeled as % of revenue
A18: Base-case expense assumptions used to complete the model: Cost of Services = 30% of revenue; Marketing = 10% of revenue; Operating Expenses = $100,000/month for Months 1–6 and $120,000/month for Months 7–12. | H18: Operating Expenses (Months 7–12) | I18: 100000 | J18: Base-case assumption: $100,000/month
I19: 120000 | J19: Base-case assumption: $120,000/month from Month 7

Sheet Assumptions
A1: Base Case Forecast Assumptions
A3: Starting Revenue (Month 1) | B3: 500000 | C3: Given
A4: Monthly Revenue Growth | B4: 0.05 | C4: Given
A5: Forecast Period (Months) | B5: 12 | C5: Given
A6: Cost of Services (% of Revenue) | C6: Not provided in the attached instructions
A7: Marketing Expense (% of Revenue) | B7: 0.3 | C7: Base-case assumption: 30% of monthly revenue
A8: Marketing Expense (Fixed Monthly Amount) | B8: 0.1 | C8: Base-case assumption: 10% of monthly revenue
A9: Operating Expenses (Months 1–6) | C9: Not used because marketing is modeled as % of revenue
A10: Operating Expenses (Months 7–12) | B10: 100000 | C10: Base-case assumption: $100,000/month
B11: 120000 | C11: Base-case assumption: $120,000/month from Month 7
